[{"startTime":"02:00","name":"熱線追蹤:440"},{"startTime":"03:00","name":"李小龍傳奇:9"},{"startTime":"04:00","name":"金曲百老匯"},{"startTime":"05:00","name":"黃金美操:225"},{"startTime":"05:30","name":"健康好簡單"},{"startTime":"06:30","name":"ＭｕＭｕ＆Ｍｅ:2"},{"startTime":"07:00","name":"早安您好-台視新聞"},{"startTime":"09:00","name":"早安最前線"},{"startTime":"10:00","name":"健康好簡單"},{"startTime":"11:00","name":"美食好簡單:180"},{"startTime":"11:30","name":"美食好簡單:297"},{"startTime":"11:58","name":"午安您好-台視新聞"},{"startTime":"13:00","name":"巔峰時代:20"},{"startTime":"15:00","name":"李小龍傳奇:10"},{"startTime":"16:00","name":"MOMO歡樂谷:26"},{"startTime":"16:30","name":"MOMO歡樂谷:27"},{"startTime":"17:00","name":"鬼太郎:34"},{"startTime":"17:30","name":"鬼太郎:35"},{"startTime":"18:00","name":"獵人:53"},{"startTime":"18:28","name":"獵人:54"},{"startTime":"18:58","name":"台視晚間新聞"},{"startTime":"20:00","name":"女人花:1"},{"startTime":"22:10","name":"醉後決定愛上你:14"},{"startTime":"23:40","name":"台視新聞世界報導"}]